{
  "RunType": "HTTP",
  "Labels": "direct",
  "StartTime": "2020-05-15T08:05:44.313809854Z",
  "RequestedQPS": "6000",
  "RequestedDuration": "1m0s",
  "ActualQPS": 5999.86942614165,
  "ActualDuration": 60001305767,
  "NumThreads": 8,
  "Version": "1.3.1",
  "DurationHistogram": {
    "Count": 360000,
    "Min": 0.000200194,
    "Max": 0.008096188,
    "Sum": 349.41950747599947,
    "Avg": 0.0009706097429888874,
    "StdDev": 0.0003788016252627808,
    "Data": [
      {
        "Start": 0.000200194,
        "End": 0.001,
        "Percent": 54.95472222222222,
        "Count": 197837
      },
      {
        "Start": 0.001,
        "End": 0.002,
        "Percent": 98.63083333333333,
        "Count": 157234
      },
      {
        "Start": 0.002,
        "End": 0.003,
        "Percent": 99.9125,
        "Count": 4614
      },
      {
        "Start": 0.003,
        "End": 0.004,
        "Percent": 99.98722222222223,
        "Count": 269
      },
      {
        "Start": 0.004,
        "End": 0.005,
        "Percent": 99.9961111111111,
        "Count": 32
      },
      {
        "Start": 0.005,
        "End": 0.006,
        "Percent": 99.99666666666667,
        "Count": 2
      },
      {
        "Start": 0.006,
        "End": 0.007,
        "Percent": 99.99777777777778,
        "Count": 4
      },
      {
        "Start": 0.007,
        "End": 0.008,
        "Percent": 99.99972222222222,
        "Count": 7
      },
      {
        "Start": 0.008,
        "End": 0.008096188,
        "Percent": 100,
        "Count": 1
      }
    ],
    "Percentiles": [
      {
        "Percentile": 50,
        "Value": 0.0009278890615358176
      },
      {
        "Percentile": 75,
        "Value": 0.0014589528982281187
      },
      {
        "Percentile": 90,
        "Value": 0.0018023900683058372
      },
      {
        "Percentile": 99,
        "Value": 0.0022880364109232813
      },
      {
        "Percentile": 99.9,
        "Value": 0.0029902470741222454
      }
    ]
  },
  "Exactly": 0,
  "RetCodes": {
    "200": 360000
  },
  "Sizes": {
    "Count": 360000,
    "Min": 100120,
    "Max": 100120,
    "Sum": 36043200000,
    "Avg": 100120,
    "StdDev": 0,
    "Data": [
      {
        "Start": 100120,
        "End": 100120,
        "Percent": 100,
        "Count": 360000
      }
    ],
    "Percentiles": null
  },
  "HeaderSizes": {
    "Count": 360000,
    "Min": 120,
    "Max": 120,
    "Sum": 43200000,
    "Avg": 120,
    "StdDev": 0,
    "Data": [
      {
        "Start": 120,
        "End": 120,
        "Percent": 100,
        "Count": 360000
      }
    ],
    "Percentiles": null
  },
  "URL": "http://localhost:5000/echo",
  "SocketCount": 8,
  "AbortOn": 0
}
