{
  "RunType": "HTTP",
  "Labels": "mesh",
  "StartTime": "2020-05-23T17:05:20.0570733Z",
  "RequestedQPS": "max",
  "RequestedDuration": "5m0s",
  "ActualQPS": 40806.20859398725,
  "ActualDuration": 300000745519,
  "NumThreads": 12,
  "Version": "1.3.1",
  "DurationHistogram": {
    "Count": 12241893,
    "Min": 0.000052767,
    "Max": 0.023804095,
    "Sum": 3595.284805468977,
    "Avg": 0.0002936869980377199,
    "StdDev": 0.0002882598359385808,
    "Data": [
      {
        "Start": 0.000052767,
        "End": 0.001,
        "Percent": 98.30440439235991,
        "Count": 12034320
      },
      {
        "Start": 0.001,
        "End": 0.002,
        "Percent": 99.80267757609056,
        "Count": 183417
      },
      {
        "Start": 0.002,
        "End": 0.003,
        "Percent": 99.90466343726416,
        "Count": 12485
      },
      {
        "Start": 0.003,
        "End": 0.004,
        "Percent": 99.93281267856204,
        "Count": 3446
      },
      {
        "Start": 0.004,
        "End": 0.005,
        "Percent": 99.95031814115677,
        "Count": 2143
      },
      {
        "Start": 0.005,
        "End": 0.006,
        "Percent": 99.96365758138876,
        "Count": 1633
      },
      {
        "Start": 0.006,
        "End": 0.007,
        "Percent": 99.97312507142482,
        "Count": 1159
      },
      {
        "Start": 0.007,
        "End": 0.008,
        "Percent": 99.980958827201,
        "Count": 959
      },
      {
        "Start": 0.008,
        "End": 0.009000000000000001,
        "Percent": 99.98719969207377,
        "Count": 764
      },
      {
        "Start": 0.009000000000000001,
        "End": 0.01,
        "Percent": 99.99081024478812,
        "Count": 442
      },
      {
        "Start": 0.01,
        "End": 0.011,
        "Percent": 99.99371829177072,
        "Count": 356
      },
      {
        "Start": 0.011,
        "End": 0.012,
        "Percent": 99.99597284504937,
        "Count": 276
      },
      {
        "Start": 0.012,
        "End": 0.014,
        "Percent": 99.99810486825852,
        "Count": 261
      },
      {
        "Start": 0.014,
        "End": 0.016,
        "Percent": 99.99950171105074,
        "Count": 171
      },
      {
        "Start": 0.016,
        "End": 0.018000000000000002,
        "Percent": 99.99979578321751,
        "Count": 36
      },
      {
        "Start": 0.018000000000000002,
        "End": 0.02,
        "Percent": 99.9999673253148,
        "Count": 21
      },
      {
        "Start": 0.02,
        "End": 0.023804095,
        "Percent": 100,
        "Count": 4
      }
    ],
    "Percentiles": [
      {
        "Percentile": 50,
        "Value": 0.0005345525974070073
      },
      {
        "Percentile": 75,
        "Value": 0.0007754454354659993
      },
      {
        "Percentile": 90,
        "Value": 0.0009199811383013946
      },
      {
        "Percentile": 99,
        "Value": 0.0014642648718493905
      },
      {
        "Percentile": 99.9,
        "Value": 0.0029542736884261038
      }
    ]
  },
  "Exactly": 0,
  "RetCodes": {
    "200": 12241893
  },
  "Sizes": {
    "Count": 12241893,
    "Min": 5118,
    "Max": 5118,
    "Sum": 62654008374,
    "Avg": 5118,
    "StdDev": 0,
    "Data": [
      {
        "Start": 5118,
        "End": 5118,
        "Percent": 100,
        "Count": 12241893
      }
    ],
    "Percentiles": null
  },
  "HeaderSizes": {
    "Count": 12241893,
    "Min": 118,
    "Max": 118,
    "Sum": 1444543374,
    "Avg": 118,
    "StdDev": 0,
    "Data": [
      {
        "Start": 118,
        "End": 118,
        "Percent": 100,
        "Count": 12241893
      }
    ],
    "Percentiles": null
  },
  "URL": "http://localhost:2002/echo",
  "SocketCount": 12,
  "AbortOn": 0
}
