{
  "RunType": "HTTP",
  "Labels": "direct",
  "StartTime": "2020-05-15T08:32:48.183270835Z",
  "RequestedQPS": "10000",
  "RequestedDuration": "1m0s",
  "ActualQPS": 5869.852834754164,
  "ActualDuration": 60000482110,
  "NumThreads": 4,
  "Version": "1.3.1",
  "DurationHistogram": {
    "Count": 352194,
    "Min": 0.000185107,
    "Max": 0.00517101,
    "Sum": 224.07611476000176,
    "Avg": 0.0006362292224171955,
    "StdDev": 0.00020820926371697528,
    "Data": [
      {
        "Start": 0.000185107,
        "End": 0.001,
        "Percent": 94.72563416753266,
        "Count": 333618
      },
      {
        "Start": 0.001,
        "End": 0.002,
        "Percent": 99.97217442659444,
        "Count": 18478
      },
      {
        "Start": 0.002,
        "End": 0.003,
        "Percent": 99.99602491808491,
        "Count": 84
      },
      {
        "Start": 0.003,
        "End": 0.004,
        "Percent": 99.99886426230998,
        "Count": 10
      },
      {
        "Start": 0.004,
        "End": 0.005,
        "Percent": 99.99971606557749,
        "Count": 3
      },
      {
        "Start": 0.005,
        "End": 0.00517101,
        "Percent": 100,
        "Count": 1
      }
    ],
    "Percentiles": [
      {
        "Percentile": 50,
        "Value": 0.0006152391507237341
      },
      {
        "Percentile": 75,
        "Value": 0.0008303064473857748
      },
      {
        "Percentile": 90,
        "Value": 0.0009593468253829992
      },
      {
        "Percentile": 99,
        "Value": 0.0018147018075549302
      },
      {
        "Percentile": 99.9,
        "Value": 0.0019862434246130543
      }
    ]
  },
  "Exactly": 0,
  "RetCodes": {
    "200": 352194
  },
  "Sizes": {
    "Count": 352194,
    "Min": 100120,
    "Max": 100120,
    "Sum": 35261663280,
    "Avg": 100120,
    "StdDev": 0,
    "Data": [
      {
        "Start": 100120,
        "End": 100120,
        "Percent": 100,
        "Count": 352194
      }
    ],
    "Percentiles": null
  },
  "HeaderSizes": {
    "Count": 352194,
    "Min": 120,
    "Max": 120,
    "Sum": 42263280,
    "Avg": 120,
    "StdDev": 0,
    "Data": [
      {
        "Start": 120,
        "End": 120,
        "Percent": 100,
        "Count": 352194
      }
    ],
    "Percentiles": null
  },
  "URL": "http://localhost:5000/echo",
  "SocketCount": 4,
  "AbortOn": 0
}
